{
  "persone": [
    {
      "nome": "Leonardo",
      "cognome": "DiCaprio",
      "data_nascita": "1974-11-11",
      "nazione": "USA",
      "lavoro": "Attore",
      "sesso":"M",
      "morto": "No"
    },
    {
      "nome": "Elon",
      "cognome": "Musk",
      "data_nascita": "1971-06-28",
      "nazione": "Sudafrica",
      "lavoro": "Imprenditore",
      "sesso":"M",
      "morto": "No"
    },
    {
      "nome": "Cristiano",
      "cognome": "Ronaldo",
      "data_nascita": "1985-02-05",
      "nazione": "Portogallo",
      "lavoro": "Calciatore",
      "sesso":"M",
      "morto": "No"
    },
    {
      "nome": "Brad",
      "cognome": "Pitt",
      "data_nascita": "1963-12-18",
      "nazione": "USA",
      "lavoro": "Attore",
      "sesso":"M",
      "morto": "No"
    },
    {
      "nome": "Scarlett",
      "cognome": "Johansson",
      "data_nascita": "1984-11-22",
      "nazione": "USA",
      "lavoro": "Attrice",
      "sesso":"F",
      "morto": "No"
    },
    {
      "nome": "Morgan",
      "cognome": "Freeman",
      "data_nascita": "1937-06-01",
      "nazione": "USA",
      "lavoro": "Attore",
      "sesso":"M",
      "morto": "No"
    },
    {
      "nome": "Taylor",
      "cognome": "Swift",
      "data_nascita": "1989-12-13",
      "nazione": "USA",
      "lavoro": "Cantautrice",
      "sesso":"F",
      "morto": "No"
    },
    {
      "nome": "Beyoncé",
      "cognome": "Knowles",
      "data_nascita": "1981-09-04",
      "nazione": "USA",
      "lavoro": "Cantautrice",
      "sesso":"F",
      "morto": "No"
    },
    {
      "nome": "Freddie",
      "cognome": "Mercury",
      "data_nascita": "1946-09-05",
      "nazione": "Regno Unito",
      "lavoro": "Cantante",
      "sesso":"M",
      "morto": "Sì"
    },
    {
      "nome": "Mark",
      "cognome": "Zuckerberg",
      "data_nascita": "1984-05-14",
      "nazione": "USA",
      "lavoro": "Imprenditore",
      "sesso":"M",
      "morto": "No"
    },
    {
      "nome": "Jeff",
      "cognome": "Bezos",
      "data_nascita": "1964-01-12",
      "nazione": "USA",
      "lavoro": "Imprenditore",
      "sesso":"M",
      "morto": "No"
    },
    {
      "nome": "Bill",
      "cognome": "Gates",
      "data_nascita": "1955-10-28",
      "nazione": "USA",
      "lavoro": "Imprenditore",
      "sesso":"M",
      "morto": "No"
    },
    {
      "nome": "Lionel",
      "cognome": "Messi",
      "data_nascita": "1987-06-24",
      "nazione": "Argentina",
      "lavoro": "Calciatore",
      "sesso":"M",
      "morto": "No"
    },
    {
      "nome": "Diego",
      "cognome": "Maradona",
      "data_nascita": "1960-10-30",
      "nazione": "Argentina",
      "lavoro": "Calciatore",
      "sesso":"M",
      "morto": "Sì"
    },
    {
      "nome": "Neymar",
      "cognome": "Jr",
      "data_nascita": "1992-02-05",
      "nazione": "Brasile",
      "lavoro": "Calciatore",
      "sesso":"M",
      "morto": "No"
    },
    {
      "nome": "Pelé",
      "cognome": "Nascimento",
      "data_nascita": "1940-10-23",
      "nazione": "Brasile",
      "lavoro": "Calciatore",
      "sesso":"M",
      "morto": "Sì"
    },
    {
      "nome": "Heath",
      "cognome": "Ledger",
      "data_nascita": "1979-04-04",
      "nazione": "Australia",
      "lavoro": "Attore",
      "sesso":"M",
      "morto": "Sì"
    },
    {
      "nome": "Whitney",
      "cognome": "Houston",
      "data_nascita": "1963-08-09",
      "nazione": "USA",
      "lavoro": "Cantautrice",
      "sesso":"F",
      "morto": "Sì"
    },
    {
      "nome": "Kobe",
      "cognome": "Bryant",
      "data_nascita": "1978-08-23",
      "nazione": "USA",
      "lavoro": "Sportivo",
      "sesso":"M",
      "morto": "Sì"
    },
    {
      "nome": "Steve",
      "cognome": "Jobs",
      "data_nascita": "1955-02-24",
      "nazione": "USA",
      "lavoro": "Imprenditore",
      "sesso":"M",
      "morto": "Sì"
    },
    {
      "nome": "Angelina",
      "cognome": "Jolie",
      "data_nascita": "1975-06-04",
      "nazione": "USA",
      "lavoro": "Attrice",
      "sesso":"F",
      "morto": "No"
    },
    {
      "nome": "Will",
      "cognome": "Smith",
      "data_nascita": "1968-09-25",
      "nazione": "USA",
      "lavoro": "Attore",
      "sesso":"M",
      "morto": "No"
    },
    {
      "nome": "Shakira",
      "cognome": "Mebarak",
      "data_nascita": "1977-02-02",
      "nazione": "Colombia",
      "lavoro": "Cantautrice",
      "sesso":"F",
      "morto": "No"
    },
    {
      "nome": "Jimi",
      "cognome": "Hendrix",
      "data_nascita": "1942-11-27",
      "nazione": "USA",
      "lavoro": "Cantante",
      "sesso":"M",
      "morto": "Sì"
    },
    {
      "nome": "Oprah",
      "cognome": "Winfrey",
      "data_nascita": "1954-01-29",
      "nazione": "USA",
      "lavoro": "Imprenditrice",
      "sesso":"F",
      "morto": "No"
    },
    {
      "nome": "David",
      "cognome": "Beckham",
      "data_nascita": "1975-05-02",
      "nazione": "Londra, Regno Unito",
      "lavoro": "Calciatore",
      "sesso":"M",
      "morto": "No"
    },
    {
      "nome": "Marilyn",
      "cognome": "Monroe",
      "data_nascita": "1926-06-01",
      "nazione": "USA",
      "lavoro": "Attrice",
      "sesso":"F",
      "morto": "Sì"
    },
    {
      "nome": "George",
      "cognome": "Clooney",
      "data_nascita": "1961-05-06",
      "nazione": "USA",
      "lavoro": "Attore",
      "sesso":"M",
      "morto": "No"
    },
    {
      "nome": "Alessandro",
      "cognome": "Ravasio",
      "data_nascita": "2007-01-26",
      "nazione": "Italia",
      "lavoro": "Studente",
      "sesso":"M",
      "morto": "No"
    },
    {
      "nome": "Simone",
      "cognome": "Bastioni",
      "data_nascita": "2006-01-30",
      "nazione": "Italia",
      "lavoro": "Studente",
      "sesso":"M",
      "morto": "Sì"
    },
    {
      "nome": "Andrea(negro)",
      "cognome": "Leoni",
      "data_nascita": "2007-",
      "nazione": "Italia",
      "lavoro": "Studente",
      "sesso":"M",
      "morto": "No"
    }
  ]
}
